LICENSE
README.md
pyproject.toml
setup.cfg
setup.py
src/dnabarcoder/dnabarcoder.py
src/dnabarcoder.egg-info/PKG-INFO
src/dnabarcoder.egg-info/SOURCES.txt
src/dnabarcoder.egg-info/dependency_links.txt
src/dnabarcoder.egg-info/requires.txt
src/dnabarcoder.egg-info/top_level.txt
src/dnabarcoder/aidscripts/addFeaturesToTaxa.py
src/dnabarcoder/aidscripts/addTextTosequenceheaders.py
src/dnabarcoder/aidscripts/addclassificationtosequenceheaders.py
src/dnabarcoder/aidscripts/assignment2funguildformat.py
src/dnabarcoder/aidscripts/cleanClassification.py
src/dnabarcoder/aidscripts/cleansequenceheaders.py
src/dnabarcoder/aidscripts/compareClassifications.py
src/dnabarcoder/aidscripts/compareCufoffs.py
src/dnabarcoder/aidscripts/fasta2matrix.py
src/dnabarcoder/aidscripts/filterClassification.py
src/dnabarcoder/aidscripts/mergesequences.py
src/dnabarcoder/aidscripts/removesequences.py
src/dnabarcoder/aidscripts/select58Ssequences.py
src/dnabarcoder/aidscripts/selectsequences.py
src/dnabarcoder/aidscripts/splitclassificationfromsequenceheaders.py
src/dnabarcoder/aidscripts/tab2fasta.py
src/dnabarcoder/aidscripts/updateClassification.py
src/dnabarcoder/analysis/computeDistribution.py
src/dnabarcoder/analysis/computeLengthDistribution.py
src/dnabarcoder/analysis/computeSim.py
src/dnabarcoder/analysis/computeVariation.py
src/dnabarcoder/analysis/overview.py
src/dnabarcoder/classification/classify.py
src/dnabarcoder/classification/evaluate.py
src/dnabarcoder/classification/search.py
src/dnabarcoder/classification/verify.py
src/dnabarcoder/classification/visualizeClassification.py
src/dnabarcoder/prediction/cluster.py
src/dnabarcoder/prediction/computeBestCutoffs.py
src/dnabarcoder/prediction/computeLocalCutoffs.py
src/dnabarcoder/prediction/mergeCutoffs.py
src/dnabarcoder/prediction/predict.py
src/dnabarcoder/prediction/removeComplexes.py
src/dnabarcoder/visualization/maketree.py
src/dnabarcoder/visualization/visualize.py