Metadata-Version: 2.1
Name: dnabarcoder
Version: 1.0.5
Summary: dnabarcoder: an open source software package for analyzing and predicting DNA sequence similarity cutoffs for fungal sequence identification
Home-page: https://github.com/vuthuyduong/dnabarcoder
Author: Duong Vu
Author-email: duong.t.vu@gmail.com
License: Apache License 2.0
Keywords: dnabarcoder
Platform: UNKNOWN
Classifier: Programming Language :: Python :: 3
License-File: LICENSE
